executor/__init__.py
executor/action_config.py
executor/base_service.py
executor/config.py
executor/env_manager.py
executor/exceptions.py
executor/executor.py
executor/git_manager.py
executor/logger.py
executor/refresh_thread.py
executor/repo_snapshots.py
executor/response.py
executor/script_runner.py
executor/service_registry.py
executor/playwright/__init__.py
executor/playwright/browser_manager.py
executor/playwright/browser_manager_cdp.py
executor/playwright/login_manager.py
snailjob/__init__.py
snailjob/args.py
snailjob/cfg.py
snailjob/config.py
snailjob/ctx.py
snailjob/deco.py
snailjob/err.py
snailjob/exec.py
snailjob/log.py
snailjob/main.py
snailjob/metrics.py
snailjob/metrics_server.py
snailjob/outbox.py
snailjob/rpc.py
snailjob/utils.py
snailjob/builtins/__init__.py
snailjob/builtins/_base.py
snailjob/builtins/_script_executor.py
snailjob/builtins/_util.py
snailjob/builtins/cmd_executor.py
snailjob/builtins/http_executor.py
snailjob/builtins/powershell_executor.py
snailjob/builtins/shell_executor.py
snailjob/grpc/__init__.py
snailjob/grpc/_rpc.py
snailjob/grpc/_server.py
snailjob/grpc/snailjob.proto
snailjob/grpc/snailjob_pb2.py
snailjob/grpc/snailjob_pb2_grpc.py
snailjob/schemas/__init__.py
snailjob/schemas/_client.py
snailjob/schemas/_common.py
snailjob/schemas/_enums.py
snailjob/schemas/_server.py
rayel_rpa_executor-0.5.49.dist-info/METADATA
rayel_rpa_executor-0.5.49.dist-info/WHEEL
rayel_rpa_executor-0.5.49.dist-info/licenses/LICENSE
rayel_rpa_executor-0.5.49.dist-info/RECORD
