Metadata-Version: 2.4
Name: rayel-rpa-executor
Version: 0.5.49
Summary: Distributed task scheduler and RPA executor with FastAPI and browser pool management
License: Apache-2.0
License-File: LICENSE
Classifier: Operating System :: OS Independent
Classifier: Programming Language :: Python :: 3
Classifier: Programming Language :: Python :: 3.12
Requires-Python: >=3.12
Requires-Dist: aiohttp>=3.10.9
Requires-Dist: apscheduler>=3.11.1
Requires-Dist: fastapi>=0.122.0
Requires-Dist: gitpython>=3.1.0
Requires-Dist: grpcio>=1.66.2
Requires-Dist: persist-queue>=1.1.0
Requires-Dist: playwright>=1.55.0
Requires-Dist: prometheus-client>=0.20.0
Requires-Dist: protobuf==5.27.2
Requires-Dist: psutil>=5.9.0
Requires-Dist: pydantic-settings>=2.0.0
Requires-Dist: pydantic>=2.7.4
Requires-Dist: python-dotenv>=1.0.1
Requires-Dist: requests>=2.32.3
Requires-Dist: tomli>=2.0.0; python_version < '3.11'
Requires-Dist: uvicorn[standard]>=0.38.0
Provides-Extra: dev
Requires-Dist: grpcio-tools>=1.66.2; extra == 'dev'
Requires-Dist: ruff>=0.3.0; extra == 'dev'
